fusio_worker_runtime-0.2.1.dist-info/licenses/LICENSE
runtime/runtime.py
runtime/generated/about.py
runtime/generated/execute.py
runtime/generated/execute_connection.py
runtime/generated/execute_context.py
runtime/generated/execute_context_app.py
runtime/generated/execute_context_user.py
runtime/generated/execute_request.py
runtime/generated/execute_request_context.py
runtime/generated/message.py
runtime/generated/response.py
runtime/generated/response_event.py
runtime/generated/response_http.py
runtime/generated/response_log.py
runtime/generated/update.py
fusio_worker_runtime-0.2.1.dist-info/METADATA
fusio_worker_runtime-0.2.1.dist-info/WHEEL
fusio_worker_runtime-0.2.1.dist-info/top_level.txt
fusio_worker_runtime-0.2.1.dist-info/RECORD
